setup.py
butler/__init__.py
python_butler.egg-info/PKG-INFO
python_butler.egg-info/SOURCES.txt
python_butler.egg-info/dependency_links.txt
python_butler.egg-info/not-zip-safe
python_butler.egg-info/top_level.txt