Metadata-Version: 1.0
Name: python-butler
Version: 0.93
Summary: Python Dictionaries and Lists on Steroids
Home-page: http://github.com/atmb4u/butler
Author: Anoop Thomas Mathew
Author-email: atmb4u@gmail.com
License: BSD
Platform: UNKNOWN
